<?xml version="1.0" encoding="UTF-8"?><record_update>
    <sys_choice action="INSERT_OR_UPDATE" field="state" table="x_terrd_snow_cicd_updateset_migration_status" version="3">
        <sys_choice action="INSERT_OR_UPDATE">
            <dependent_value/>
            <element>state</element>
            <hint/>
            <inactive>false</inactive>
            <label>ATF Test In Progress</label>
            <language>en</language>
            <name>x_terrd_snow_cicd_updateset_migration_status</name>
            <sequence>0</sequence>
            <sys_created_by>Mahesh.Mani</sys_created_by>
            <sys_created_on>2019-12-31 18:34:26</sys_created_on>
            <sys_domain>global</sys_domain>
            <sys_id>cf471a7d1b064454163233fccd4bcbed</sys_id>
            <sys_mod_count>0</sys_mod_count>
            <sys_updated_by>Mahesh.Mani</sys_updated_by>
            <sys_updated_on>2019-12-31 18:34:26</sys_updated_on>
            <value>ATF Test In Progress</value>
        </sys_choice>
        <sys_choice action="INSERT_OR_UPDATE">
            <dependent_value/>
            <element>state</element>
            <hint/>
            <inactive>false</inactive>
            <label>Test Passed</label>
            <language>en</language>
            <name>x_terrd_snow_cicd_updateset_migration_status</name>
            <sequence>1</sequence>
            <sys_created_by>Mahesh.Mani</sys_created_by>
            <sys_created_on>2019-12-31 18:14:14</sys_created_on>
            <sys_domain>global</sys_domain>
            <sys_id>d7a2963d1b064454163233fccd4bcb95</sys_id>
            <sys_mod_count>1</sys_mod_count>
            <sys_updated_by>Mahesh.Mani</sys_updated_by>
            <sys_updated_on>2019-12-31 18:34:26</sys_updated_on>
            <value>Test Passed</value>
        </sys_choice>
        <sys_choice action="INSERT_OR_UPDATE">
            <dependent_value/>
            <element>state</element>
            <hint/>
            <inactive>false</inactive>
            <label>Test Failed</label>
            <language>en</language>
            <name>x_terrd_snow_cicd_updateset_migration_status</name>
            <sequence>2</sequence>
            <sys_created_by>Mahesh.Mani</sys_created_by>
            <sys_created_on>2019-12-31 18:14:14</sys_created_on>
            <sys_domain>global</sys_domain>
            <sys_id>9fa2963d1b064454163233fccd4bcb96</sys_id>
            <sys_mod_count>1</sys_mod_count>
            <sys_updated_by>Mahesh.Mani</sys_updated_by>
            <sys_updated_on>2019-12-31 18:34:26</sys_updated_on>
            <value>Test Failed</value>
        </sys_choice>
        <sys_choice action="INSERT_OR_UPDATE">
            <dependent_value/>
            <element>state</element>
            <hint/>
            <inactive>false</inactive>
            <label>In Code Review(Pull Requested)</label>
            <language>en</language>
            <name>x_terrd_snow_cicd_updateset_migration_status</name>
            <sequence>3</sequence>
            <sys_created_by>Mahesh.Mani</sys_created_by>
            <sys_created_on>2019-12-31 18:14:14</sys_created_on>
            <sys_domain>global</sys_domain>
            <sys_id>97a252711b464454163233fccd4bcb2b</sys_id>
            <sys_mod_count>2</sys_mod_count>
            <sys_updated_by>Mahesh.Mani</sys_updated_by>
            <sys_updated_on>2020-01-02 23:15:21</sys_updated_on>
            <value>In Code Review</value>
        </sys_choice>
        <sys_choice action="INSERT_OR_UPDATE">
            <dependent_value/>
            <element>state</element>
            <hint/>
            <inactive>false</inactive>
            <label>Preview Completed</label>
            <language>en</language>
            <name>x_terrd_snow_cicd_updateset_migration_status</name>
            <sequence>4</sequence>
            <sys_created_by>Mahesh.Mani</sys_created_by>
            <sys_created_on>2019-12-31 18:14:14</sys_created_on>
            <sys_domain>global</sys_domain>
            <sys_id>57a252711b464454163233fccd4bcb2c</sys_id>
            <sys_mod_count>5</sys_mod_count>
            <sys_updated_by>Mahesh.Mani</sys_updated_by>
            <sys_updated_on>2020-01-17 20:19:46</sys_updated_on>
            <value>Preview Completed</value>
        </sys_choice>
        <sys_choice action="INSERT_OR_UPDATE">
            <dependent_value/>
            <element>state</element>
            <hint/>
            <inactive>false</inactive>
            <label>Failed</label>
            <language>en</language>
            <name>x_terrd_snow_cicd_updateset_migration_status</name>
            <sequence>6</sequence>
            <sys_created_by>Mahesh.Mani</sys_created_by>
            <sys_created_on>2020-01-03 19:57:33</sys_created_on>
            <sys_domain>global</sys_domain>
            <sys_id>340702721bce8054e8e30dc8cd4bcb59</sys_id>
            <sys_mod_count>4</sys_mod_count>
            <sys_updated_by>Mahesh.Mani</sys_updated_by>
            <sys_updated_on>2020-01-17 20:19:23</sys_updated_on>
            <value>Failed</value>
        </sys_choice>
        <sys_choice_set action="INSERT_OR_UPDATE">
            <element>state</element>
            <name>x_terrd_snow_cicd_updateset_migration_status</name>
            <sys_class_name>sys_choice_set</sys_class_name>
            <sys_created_by>Mahesh.Mani</sys_created_by>
            <sys_created_on>2019-12-31 18:14:14</sys_created_on>
            <sys_customer_update>false</sys_customer_update>
            <sys_id>481d2fa41b2ac090e8e30dc8cd4bcbce</sys_id>
            <sys_mod_count>0</sys_mod_count>
            <sys_name>state</sys_name>
            <sys_package display_value="SNOW CICD" source="x_terrd_snow_cicd">189529481b0ec0d0e8e30dc8cd4bcb4b</sys_package>
            <sys_policy/>
            <sys_replace_on_upgrade>false</sys_replace_on_upgrade>
            <sys_scope display_value="SNOW CICD">189529481b0ec0d0e8e30dc8cd4bcb4b</sys_scope>
            <sys_update_name>sys_choice_x_terrd_snow_cicd_updateset_migration_status_state</sys_update_name>
            <sys_updated_by>Mahesh.Mani</sys_updated_by>
            <sys_updated_on>2019-12-31 18:14:14</sys_updated_on>
        </sys_choice_set>
    </sys_choice>
</record_update>
